h5lib/__init__.py
h5lib/library.py
h5lib/py.typed
h5lib/reader.py
h5lib/types.py
h5lib/writer.py
h5lib-0.1.2.dist-info/LICENSE
h5lib-0.1.2.dist-info/METADATA
h5lib-0.1.2.dist-info/WHEEL
h5lib-0.1.2.dist-info/RECORD
